sysdynpy/__init__.py
sysdynpy/dynamicvariable.py
sysdynpy/exporter.py
sysdynpy/flow.py
sysdynpy/parameter.py
sysdynpy/simulator.py
sysdynpy/stock.py
sysdynpy/system.py
sysdynpy/systemelement.py
sysdynpy/test/__init__.py
SysDynPy-0.1.0.dist-info/LICENSE.txt
SysDynPy-0.1.0.dist-info/METADATA
SysDynPy-0.1.0.dist-info/WHEEL
SysDynPy-0.1.0.dist-info/top_level.txt
SysDynPy-0.1.0.dist-info/RECORD
