Metadata-Version: 2.1
Name: SysDynPy
Version: 0.1.0
Summary: A framework to build System Dynamics models
Home-page: https://github.com/t16h05008/SysDynPy
Author: Tim Herker
Author-email: tim.herker@stud.hs-bochum.de
License: LICENSE.txt
Platform: UNKNOWN
Classifier: Programming Language :: Python :: 3
Classifier: License :: OSI Approved :: MIT License
Classifier: Operating System :: OS Independent
Requires-Dist: matplotlib
